fastdict/__init__.py
fastdict/fastdict.py
fastdict-0.1.1.dist-info/LICENSE
fastdict-0.1.1.dist-info/METADATA
fastdict-0.1.1.dist-info/WHEEL
fastdict-0.1.1.dist-info/top_level.txt
fastdict-0.1.1.dist-info/zip-safe
fastdict-0.1.1.dist-info/RECORD
