Metadata-Version: 2.1
Name: fastdict
Version: 0.1.1
Summary: Python fastdict with attribute
Home-page: https://github.com/StevenBaby/fastdict
Author: StevenKang
Author-email: kangweibaby@163.com
License: MIT
Platform: any
Classifier: License :: OSI Approved :: MIT License
Classifier: Intended Audience :: Developers
Classifier: Operating System :: OS Independent
Classifier: Programming Language :: Python :: 3
